tspyo/__init__.py
tspyo/singletons.py
tspyo-0.1.0.dev0.dist-info/LICENSE
tspyo-0.1.0.dev0.dist-info/METADATA
tspyo-0.1.0.dev0.dist-info/WHEEL
tspyo-0.1.0.dev0.dist-info/top_level.txt
tspyo-0.1.0.dev0.dist-info/RECORD
